{
  "parent": "archeon:flower_advancement_roseypia",
  "criteria": {
    "flower_advancement_pink_lycoris": {
      "conditions": {
        "items": [
          {
            "items": [
              "archeon:lycoris_radiata"
            ]
          }
        ]
      },
      "trigger": "minecraft:inventory_changed"
    }
  },
  "display": {
    "announce_to_chat": true,
    "description": {
      "translate": "advancements.flower_advancement_pink_lycoris.descr"
    },
    "frame": "task",
    "hidden": false,
    "icon": {
      "item": "archeon:lycoris_radiata"
    },
    "show_toast": true,
    "title": {
      "translate": "advancements.flower_advancement_pink_lycoris.title"
    }
  },
  "requirements": [
    [
      "flower_advancement_pink_lycoris"
    ]
  ],
  "sends_telemetry_event": true
}
